HISTORY.txt
LICENSE.txt
MANIFEST.in
README.txt
setup.py
doc/Makefile
doc/api.rst
doc/command-line.rst
doc/conf.py
doc/index.rst
doc/installation.rst
doc/make.bat
doc/prerequisites.rst
doc/_build/index.rst
doc/locale/ja/LC_MESSAGES/api.po
doc/locale/ja/LC_MESSAGES/command-line.po
doc/locale/ja/LC_MESSAGES/index.po
doc/locale/ja/LC_MESSAGES/installation.po
doc/locale/ja/LC_MESSAGES/prerequisites.po
ironpycompiler/__init__.py
ironpycompiler/compiler.py
ironpycompiler/constants.py
ironpycompiler/detect.py
ironpycompiler/exceptions.py
ironpycompiler/ipy2asm.py
ironpycompiler.egg-info/PKG-INFO
ironpycompiler.egg-info/SOURCES.txt
ironpycompiler.egg-info/dependency_links.txt
ironpycompiler.egg-info/entry_points.txt
ironpycompiler.egg-info/top_level.txt