Metadata-Version: 1.1
Name: ironpycompiler
Version: 0.10.0
Summary: Compile IronPython scripts into a stand-alone .NET assembly.
Home-page: https://github.com/hamukichi/ironpycompiler
Author: Hamukichi (Nombiri)
Author-email: hamukichi-dev@outlook.jp
License: MIT License
Keywords: ironpython,.net,assembly,executable,compile,stand-alone,pyc.py
Platform: UNKNOWN
Classifier: Development Status :: 4 - Beta
Classifier: Intended Audience :: Developers
Classifier: License :: OSI Approved :: MIT License
Classifier: Operating System :: Microsoft :: Windows
Classifier: Programming Language :: Python
Classifier: Programming Language :: Python :: 2
Classifier: Programming Language :: Python :: 2.7
Classifier: Programming Language :: Python :: Implementation :: CPython
Classifier: Topic :: Software Development
Classifier: Topic :: System :: Software Distribution
Provides: ironpycompiler
